__init__.py
mongodb_backup_exporter.py
mongodb_backup_exporter-0.3.213.dist-info/LICENSE
mongodb_backup_exporter-0.3.213.dist-info/METADATA
mongodb_backup_exporter-0.3.213.dist-info/WHEEL
mongodb_backup_exporter-0.3.213.dist-info/top_level.txt
mongodb_backup_exporter-0.3.213.dist-info/RECORD
