Metadata-Version: 2.1
Name: mongodb-backup-exporter
Version: 0.3.213
Summary: A tool to export MongoDB collections to JSON or CSV files
Home-page: https://github.com/jorgecardona/mongodb-backup-exporter
Author: Jorge Cardona
Classifier: Programming Language :: Python :: 3
Classifier: License :: OSI Approved :: MIT License
Classifier: Operating System :: OS Independent
Requires-Python: >=3.6
License-File: LICENSE
Requires-Dist: pymongo
